sphinxcontrib/analytics/__init__.py
sphinxcontrib/analytics/errors.py
sphinxcontrib/analytics/events.py
sphinxcontrib/analytics/_static/google-analytics.js_t
sphinxcontrib/analytics/_static/matomo-analytics.js_t
sphinxcontrib_analytics-1.0.0.dev6.dist-info/LICENSE
sphinxcontrib_analytics-1.0.0.dev6.dist-info/METADATA
sphinxcontrib_analytics-1.0.0.dev6.dist-info/WHEEL
sphinxcontrib_analytics-1.0.0.dev6.dist-info/top_level.txt
sphinxcontrib_analytics-1.0.0.dev6.dist-info/RECORD
